fairyland/__init__.py
fairyland/framework/__init__.py
fairyland/framework/core/__init__.py
fairyland/framework/core/abstracts/__init__.py
fairyland/framework/core/abstracts/enumerate/__init__.py
fairyland/framework/core/abstracts/enumerate/_enumerate.py
fairyland/framework/core/constants/__init__.py
fairyland/framework/core/generals/__init__.py
fairyland/framework/core/services/__init__.py
fairyland/framework/modules/__init__.py
fairyland/framework/modules/constants/__init__.py
fairyland/framework/modules/decorators/__init__.py
fairyland/framework/modules/decorators/_method.py
fairyland/framework/modules/exceptions/__init__.py
fairyland/framework/modules/generals/__init__.py
fairyland/framework/modules/generals/_enumerate.py
fairyland/framework/modules/journals/__init__.py
fairyland/framework/modules/journals/_journal.py
fairyland/framework/utils/__init__.py
fairyland/framework/utils/constants/__init__.py
fairyland/framework/utils/constants/release/__init__.py
fairyland/framework/utils/generals/__init__.py
fairyland/framework/utils/generals/_datetime.py
fairyland/framework/utils/generals/_generals.py
fairyland/framework/utils/publish/__init__.py
fairyland/framework/utils/publish/_package.py
test/__init__.py
test/test.py
PyFairyland-0.0.6.dist-info/LICENSE.txt
PyFairyland-0.0.6.dist-info/METADATA
PyFairyland-0.0.6.dist-info/WHEEL
PyFairyland-0.0.6.dist-info/top_level.txt
PyFairyland-0.0.6.dist-info/RECORD
