Metadata-Version: 2.1
Name: PyFairyland
Version: 0.0.6
Summary: personally developed Python library.
Home-page: https://github.com/AustinFairyland/AustinFairylandRepository
Author: Lionel Johnson
Author-email: fairylandfuture@outlook.com
Keywords: fairyland,Fairyland,pyfairyland,PyFairyland,fairy,Fairy
Classifier: Programming Language :: Python :: 3
Classifier: Programming Language :: Python :: 3.7
Classifier: Programming Language :: Python :: 3.8
Classifier: Programming Language :: Python :: 3.9
Classifier: Programming Language :: Python :: 3.10
Classifier: Programming Language :: Python :: 3.11
Classifier: Programming Language :: Python :: 3.12
Classifier: Programming Language :: Python :: Implementation :: CPython
Classifier: Programming Language :: Python :: Implementation :: PyPy
Classifier: Programming Language :: SQL
Classifier: Framework :: Django :: 2
Classifier: Framework :: Django :: 3
Classifier: Framework :: Django :: 4
Classifier: Framework :: Flask
Classifier: Framework :: FastAPI
Classifier: Framework :: Flake8
Classifier: Framework :: IPython
Classifier: Framework :: Jupyter
Classifier: Framework :: Scrapy
Classifier: Natural Language :: English
Classifier: Natural Language :: Chinese (Simplified)
Classifier: Operating System :: Microsoft :: Windows :: Windows 11
Classifier: Operating System :: POSIX :: Linux
Classifier: Operating System :: POSIX :: Linux
Classifier: Topic :: Software Development :: Libraries :: Python Modules
Classifier: Topic :: Software Development :: Libraries :: Application Frameworks
Classifier: Topic :: Software Development :: Version Control :: Git
Classifier: Topic :: System :: Operating System Kernels :: Linux
Classifier: License :: OSI Approved :: GNU Affero General Public License v3 or later (AGPLv3+)
Requires-Python: >=3.7
License-File: LICENSE.txt
Requires-Dist: pip-review
Requires-Dist: pip-autoremove
Requires-Dist: black
Requires-Dist: python-dotenv
Requires-Dist: loguru
Requires-Dist: enums
Requires-Dist: pymysql
Requires-Dist: psycopg2-binary
Requires-Dist: pyyaml
Requires-Dist: requests
Requires-Dist: tornado
Requires-Dist: pandas
Requires-Dist: django
Requires-Dist: django-stubs
Requires-Dist: djangorestframework
Requires-Dist: django-cors-headers
